trexio_tools/__init__.py
trexio_tools/trexio_run.py
trexio_tools/converters/__init__.py
trexio_tools/converters/cart_sphe.py
trexio_tools/converters/convert_back_end.py
trexio_tools/converters/convert_from.py
trexio_tools/converters/convert_to.py
trexio_tools/converters/crystal_to_trexio.py
trexio_tools/converters/orca_to_trexio.py
trexio_tools/converters/pyscf_to_trexio.py
trexio_tools/group_tools/__init__.py
trexio_tools/group_tools/ao.py
trexio_tools/group_tools/basis.py
trexio_tools/group_tools/check_basis.py
trexio_tools/group_tools/check_mos.py
trexio_tools/group_tools/determinant.py
trexio_tools/group_tools/mo.py
trexio_tools/group_tools/nao.py
trexio_tools/group_tools/nucleus.py
trexio_tools-0.9.0.dist-info/licenses/LICENSE
trexio_tools-0.9.0.dist-info/METADATA
trexio_tools-0.9.0.dist-info/WHEEL
trexio_tools-0.9.0.dist-info/entry_points.txt
trexio_tools-0.9.0.dist-info/top_level.txt
trexio_tools-0.9.0.dist-info/RECORD
