Metadata-Version: 2.4
Name: trexio-tools
Version: 0.9.0
Summary: Set of tools for TREXIO files
Home-page: https://github.com/TREX-CoE/trexio_tools
Author: TREX-CoE
Author-email: evgenyp@qubit-pharmaceuticals.com
License: BSD 3-Clause License
Project-URL: Bug Tracker, https://github.com/TREX-CoE/trexio_tools/issues
Classifier: Programming Language :: Python :: 3
Classifier: License :: OSI Approved :: BSD License
Classifier: Operating System :: OS Independent
Requires-Python: >=3.8
License-File: LICENSE
Requires-Dist: docopt
Requires-Dist: resultsFile>=2.4
Requires-Dist: trexio>=1.2
Dynamic: license-file
